axya_whisper/__init__.py
axya_whisper/main.py
axya_whisper/service.py
axya_whisper-0.1.0.dist-info/METADATA
axya_whisper-0.1.0.dist-info/WHEEL
axya_whisper-0.1.0.dist-info/entry_points.txt
axya_whisper-0.1.0.dist-info/top_level.txt
axya_whisper-0.1.0.dist-info/RECORD
