Metadata-Version: 2.1
Name: axya-whisper
Version: 0.1.0
Requires-Python: >=3.6
Requires-Dist: pywin32
